ai_essay_grader/__init__.py
ai_essay_grader/__main__.py
ai_essay_grader/cli.py
ai_essay_grader/py.typed
ai_essay_grader/student_evaluator/__init__.py
ai_essay_grader/student_evaluator/cli.py
ai_essay_grader/student_evaluator/csv_processor.py
ai_essay_grader/student_evaluator/evaluator.py
ai_essay_grader/student_evaluator/file_utils.py
ai_essay_grader/student_evaluator/grader.py
ai_essay_grader/student_evaluator/models.py
ai_essay_grader/trainer/__init__.py
ai_essay_grader/trainer/cli.py
ai_essay_grader/trainer/finetuner.py
ai_essay_grader/trainer/generator.py
ai_essay_grader/trainer/merge.py
ai_essay_grader/trainer/uploader.py
ai_essay_grader/trainer/validator.py
ai_essay_grader-0.13.1.dist-info/LICENSE
ai_essay_grader-0.13.1.dist-info/METADATA
ai_essay_grader-0.13.1.dist-info/WHEEL
ai_essay_grader-0.13.1.dist-info/entry_points.txt
ai_essay_grader-0.13.1.dist-info/top_level.txt
ai_essay_grader-0.13.1.dist-info/RECORD
