Metadata-Version: 2.2
Name: ai-essay-grader
Version: 0.13.1
Summary: This repository provides a modular framework for generating, validating, merging, uploading, and fine-tuning OpenAI GPT-4o-mini models using structured JSONL datasets.
Author-email: Mark Moreno <mamoreno@aldineisd.org>
License: MIT
Project-URL: Bug Tracker, https://github.com/markm-io/ai-essay-grader/issues
Project-URL: Changelog, https://github.com/markm-io/ai-essay-grader/blob/main/CHANGELOG.md
Project-URL: documentation, https://ai-essay-grader.readthedocs.io
Project-URL: repository, https://github.com/markm-io/ai-essay-grader
Classifier: Development Status :: 2 - Pre-Alpha
Classifier: Intended Audience :: Developers
Classifier: Natural Language :: English
Classifier: Operating System :: OS Independent
Classifier: Programming Language :: Python :: 3.9
Classifier: Programming Language :: Python :: 3.10
Classifier: Programming Language :: Python :: 3.11
Classifier: Programming Language :: Python :: 3.12
Classifier: Programming Language :: Python :: 3.13
Classifier: Topic :: Software Development :: Libraries
Requires-Python: >=3.9
License-File: LICENSE
Requires-Dist: aiocsv>=1.3.2
Requires-Dist: aiofiles>=24.1.0
Requires-Dist: openai>=1.64.0
Requires-Dist: pandas>=2.2.3
Requires-Dist: rich>=10
Requires-Dist: tiktoken>=0.9.0
Requires-Dist: typer<1,>=0.15
